python_ifconfig_me/__init__.py
python_ifconfig_me/cli.py
python_ifconfig_me/core/__init__.py
python_ifconfig_me/core/getPublicIP.py
python_ifconfig_me/core/ipObject.py
python_ifconfig_me/core/ipretriever/__init__.py
python_ifconfig_me/core/ipretriever/callbackIPRetriever.py
python_ifconfig_me/core/ipretriever/ipRetriever.py
python_ifconfig_me/core/ipretriever/simpleTextIPRetriever.py
python_ifconfig_me/core/vote/__init__.py
python_ifconfig_me/core/vote/statisticsInformationItem.py
python_ifconfig_me/core/vote/votingStrategy.py
python_ifconfig_me/utils/__init__.py
python_ifconfig_me/utils/async_.py
python_ifconfig_me-0.0.2.dist-info/LICENSE
python_ifconfig_me-0.0.2.dist-info/METADATA
python_ifconfig_me-0.0.2.dist-info/WHEEL
python_ifconfig_me-0.0.2.dist-info/entry_points.txt
python_ifconfig_me-0.0.2.dist-info/RECORD
