Metadata-Version: 2.1
Name: python-ifconfig-me
Version: 0.0.2
Summary: This is a tool to get public ip of your machine
Home-page: https://github.com/catwang01/python-ifconfig-me
License: GPL-3.0-only
Keywords: ifconfig,ip,public ip,python,network,ipv4,ipv6
Author: catwang01
Author-email: edwardelricwzx@gmail.com
Requires-Python: >=3.9,<4.0
Classifier: License :: OSI Approved :: GNU General Public License v3 (GPLv3)
Classifier: Programming Language :: Python :: 3
Classifier: Programming Language :: Python :: 3.9
Classifier: Programming Language :: Python :: 3.10
Classifier: Programming Language :: Python :: 3.11
Classifier: Programming Language :: Python :: 3.12
Classifier: Programming Language :: Python :: 3.13
Requires-Dist: aiohttp (>=3.9.1,<4.0.0)
Requires-Dist: typing-extensions (>=4.0.1,<5.0.0) ; python_full_version <= "3.10.0"
Project-URL: Repository, https://github.com/catwang01/python-ifconfig-me
